cmd2_ext_test/__init__.py
cmd2_ext_test/cmd2_ext_test.py
cmd2_ext_test/py.typed
cmd2_ext_test-2.0.0.dist-info/METADATA
cmd2_ext_test-2.0.0.dist-info/WHEEL
cmd2_ext_test-2.0.0.dist-info/top_level.txt
cmd2_ext_test-2.0.0.dist-info/RECORD
